binance_sdk_derivatives_trading_options/__init__.py
binance_sdk_derivatives_trading_options/derivatives_trading_options.py
binance_sdk_derivatives_trading_options/metadata.py
binance_sdk_derivatives_trading_options/rest_api/__init__.py
binance_sdk_derivatives_trading_options/rest_api/api/__init__.py
binance_sdk_derivatives_trading_options/rest_api/api/account_api.py
binance_sdk_derivatives_trading_options/rest_api/api/market_data_api.py
binance_sdk_derivatives_trading_options/rest_api/api/market_maker_block_trade_api.py
binance_sdk_derivatives_trading_options/rest_api/api/market_maker_endpoints_api.py
binance_sdk_derivatives_trading_options/rest_api/api/trade_api.py
binance_sdk_derivatives_trading_options/rest_api/api/user_data_streams_api.py
binance_sdk_derivatives_trading_options/rest_api/models/__init__.py
binance_sdk_derivatives_trading_options/rest_api/models/accept_block_trade_order_response.py
binance_sdk_derivatives_trading_options/rest_api/models/accept_block_trade_order_response_legs_inner.py
binance_sdk_derivatives_trading_options/rest_api/models/account_block_trade_list_response.py
binance_sdk_derivatives_trading_options/rest_api/models/account_block_trade_list_response_inner.py
binance_sdk_derivatives_trading_options/rest_api/models/account_block_trade_list_response_inner_legs_inner.py
binance_sdk_derivatives_trading_options/rest_api/models/account_funding_flow_response.py
binance_sdk_derivatives_trading_options/rest_api/models/account_funding_flow_response_inner.py
binance_sdk_derivatives_trading_options/rest_api/models/account_trade_list_response.py
binance_sdk_derivatives_trading_options/rest_api/models/account_trade_list_response_inner.py
binance_sdk_derivatives_trading_options/rest_api/models/auto_cancel_all_open_orders_response.py
binance_sdk_derivatives_trading_options/rest_api/models/cancel_all_option_orders_by_underlying_response.py
binance_sdk_derivatives_trading_options/rest_api/models/cancel_all_option_orders_on_specific_symbol_response.py
binance_sdk_derivatives_trading_options-5.1.0.dist-info/METADATA
binance_sdk_derivatives_trading_options-5.1.0.dist-info/WHEEL
binance_sdk_derivatives_trading_options-5.1.0.dist-info/licenses/LICENCE
binance_sdk_derivatives_trading_options-5.1.0.dist-info/RECORD
